MANIFEST.in
README.md
setup.py
GridCal/ExecuteGridCal.py
GridCal/LICENSE.txt
GridCal/__init__.py
GridCal/__version__.py
GridCal/update.py
GridCal.egg-info/PKG-INFO
GridCal.egg-info/SOURCES.txt
GridCal.egg-info/dependency_links.txt
GridCal.egg-info/requires.txt
GridCal.egg-info/top_level.txt
GridCal/Engine/__init__.py
GridCal/Engine/basic_structures.py
GridCal/Engine/grid_analysis.py
GridCal/Engine/Core/__init__.py
GridCal/Engine/Core/admittance_matrices.py
GridCal/Engine/Core/common_functions.py
GridCal/Engine/Core/multi_circuit.py
GridCal/Engine/Core/snapshot_opf_data.py
GridCal/Engine/Core/snapshot_pf_data.py
GridCal/Engine/Core/time_series_opf_data.py
GridCal/Engine/Core/time_series_pf_data.py
GridCal/Engine/Core/topology.py
GridCal/Engine/Core/Compilers/__init__.py
GridCal/Engine/Core/Compilers/circuit_to_bentayga.py
GridCal/Engine/Core/Compilers/circuit_to_data.py
GridCal/Engine/Core/Compilers/circuit_to_data2.py
GridCal/Engine/Core/Compilers/circuit_to_newton_pa.py
GridCal/Engine/Core/Compilers/circuit_to_pgm.py
GridCal/Engine/Core/DataStructures/__init__.py
GridCal/Engine/Core/DataStructures/battery_data.py
GridCal/Engine/Core/DataStructures/branch_data.py
GridCal/Engine/Core/DataStructures/bus_data.py
GridCal/Engine/Core/DataStructures/dc_lines_data.py
GridCal/Engine/Core/DataStructures/generator_data.py
GridCal/Engine/Core/DataStructures/hvdc_data.py
GridCal/Engine/Core/DataStructures/lines_data.py
GridCal/Engine/Core/DataStructures/load_data.py
GridCal/Engine/Core/DataStructures/shunt_data.py
GridCal/Engine/Core/DataStructures/static_generator_data.py
GridCal/Engine/Core/DataStructures/transformer_data.py
GridCal/Engine/Core/DataStructures/upfc_data.py
GridCal/Engine/Core/DataStructures/vsc_data.py
GridCal/Engine/Devices/__init__.py
GridCal/Engine/Devices/battery.py
GridCal/Engine/Devices/branch.py
GridCal/Engine/Devices/bus.py
GridCal/Engine/Devices/contingency.py
GridCal/Engine/Devices/contingency_group.py
GridCal/Engine/Devices/dc_line.py
GridCal/Engine/Devices/editable_device.py
GridCal/Engine/Devices/enumerations.py
GridCal/Engine/Devices/external_grid.py
GridCal/Engine/Devices/generator.py
