Metadata-Version: 2.1
Name: GridCal
Version: 4.7.9
Summary: GridCal is a Power Systems simulation program intended for professional use and research
Home-page: https://github.com/SanPen/GridCal
Author: Santiago Peñate Vera et. Al.
Author-email: santiago.penate.vera@gmail.com
License: LGPL
Keywords: power systems planning
Classifier: License :: OSI Approved :: GNU Library or Lesser General Public License (LGPL)
Classifier: Programming Language :: Python :: 3.6
Classifier: Programming Language :: Python :: 3.7
Classifier: Programming Language :: Python :: 3.8
Classifier: Programming Language :: Python :: 3.9
Requires-Python: >=3.6
Provides-Extra: gch5 files
